subject_imagefield/__init__.py
subject_imagefield/config.py
subject_imagefield/fields.py
subject_imagefield/forms.py
subject_imagefield/widgets.py
subject_imagefield/locale/it/LC_MESSAGES/django.mo
subject_imagefield/locale/it/LC_MESSAGES/django.po
subject_imagefield/templates/subject_imagefield/widgets/subject_image.html
django_subject_imagefield-0.2.13.dist-info/LICENSE
django_subject_imagefield-0.2.13.dist-info/METADATA
django_subject_imagefield-0.2.13.dist-info/WHEEL
django_subject_imagefield-0.2.13.dist-info/top_level.txt
django_subject_imagefield-0.2.13.dist-info/RECORD
